pandasai_yfinance/__init__.py
pandasai_yfinance-0.1.5.dist-info/METADATA
pandasai_yfinance-0.1.5.dist-info/WHEEL
pandasai_yfinance-0.1.5.dist-info/RECORD
