Metadata-Version: 2.4
Name: pandasai-yfinance
Version: 0.1.5
Summary: YFinance integration for PandasAI
License: MIT
Author: Gabriele Venturi
Requires-Python: >=3.9,<3.12
Classifier: License :: OSI Approved :: MIT License
Classifier: Programming Language :: Python :: 3
Classifier: Programming Language :: Python :: 3.9
Classifier: Programming Language :: Python :: 3.10
Classifier: Programming Language :: Python :: 3.11
Requires-Dist: pandasai (>=3.0.0b4)
Requires-Dist: pyarrow (>=14.0.1,<19.0.0)
Requires-Dist: yfinance (>=0.2.35,<0.3.0)
